aos_pyez-0.7.1-py2.7-nspkg.pth
aos_pyez-0.7.1.data/scripts/aosom-export-neo4j.py
aos_pyez-0.7.1.dist-info/DESCRIPTION.rst
aos_pyez-0.7.1.dist-info/METADATA
aos_pyez-0.7.1.dist-info/RECORD
aos_pyez-0.7.1.dist-info/WHEEL
aos_pyez-0.7.1.dist-info/metadata.json
aos_pyez-0.7.1.dist-info/namespace_packages.txt
aos_pyez-0.7.1.dist-info/top_level.txt
apstra/aosom/__init__.py
apstra/aosom/exc.py
apstra/aosom/session.py
apstra/aosom/session_api.py
apstra/aosom/swm.py
apstra/aosom/blueprints/__init__.py
apstra/aosom/blueprints/blueprint_item.py
apstra/aosom/blueprints/blueprints.py
apstra/aosom/blueprints/configs.py
apstra/aosom/blueprints/graph.py
apstra/aosom/blueprints/graph_node.py
apstra/aosom/blueprints/graph_relationship.py
apstra/aosom/blueprints/registry.py
apstra/aosom/blueprints/resource_groups.py
apstra/aosom/blueprints/widget.py
apstra/aosom/design_elements/__init__.py
apstra/aosom/design_elements/design_templates.py
apstra/aosom/design_elements/logical_device_maps.py
apstra/aosom/design_elements/logical_devices.py
apstra/aosom/design_elements/rack_types.py
apstra/aosom/resource_pools/__init__.py
apstra/aosom/resource_pools/asn_pools.py
apstra/aosom/resource_pools/ext_rtrs.py
apstra/aosom/resource_pools/ip_pools.py
apstra/aosom/system_elements/__init__.py
apstra/aosom/system_elements/device_telemetry.py
apstra/aosom/system_elements/devices.py
apstra/aosom/system_elements/hcl.py
apstra/aosom/utils/__init__.py
apstra/aosom/utils/collection.py
apstra/aosom/utils/collection_item.py
apstra/aosom/utils/collection_mapper.py
apstra/aosom/utils/dynmodldr.py
apstra/aosom/utils/indexer.py
