Metadata-Version: 2.0
Name: aos-pyez
Version: 0.7.1
Summary: Python wrapper library for Apstra AOS REST API 
Home-page: https://github.com/Apstra/aos-pyez
Author: Jeremy Schulman
Author-email: jeremy@apstra.com
License: Apache 2.0
Keywords: networking automation vendor-agnostic
Platform: UNKNOWN
Classifier: Development Status :: 3 - Alpha
Classifier: Intended Audience :: Developers
Classifier: Intended Audience :: Information Technology
Classifier: Intended Audience :: System Administrators
Classifier: Intended Audience :: Telecommunications Industry
Classifier: License :: OSI Approved :: Apache Software License
Classifier: Operating System :: OS Independent
Classifier: Programming Language :: Python
Classifier: Programming Language :: Python :: 2.7
Classifier: Topic :: Software Development :: Libraries
Classifier: Topic :: Software Development :: Libraries :: Application Frameworks
Classifier: Topic :: Software Development :: Libraries :: Python Modules
Classifier: Topic :: System :: Networking
Requires-Dist: bidict
Requires-Dist: cached-property
Requires-Dist: enum34
Requires-Dist: graphene
Requires-Dist: jmespath
Requires-Dist: pyyaml
Requires-Dist: requests
Requires-Dist: retrying
Requires-Dist: semantic-version
